{
    "centers": [
        [
            0.023455239832401276,
            -0.3506677746772766,
            -0.035666875541210175
        ],
        [
            -0.005784905981272459,
            -0.1369076669216156,
            0.0020116453524678946
        ],
        [
            0.0041076550260186195,
            -0.23345127701759338,
            -0.0014214757829904556
        ],
        [
            -0.022840090095996857,
            -0.2152538150548935,
            0.029271936044096947
        ],
        [
            -0.023599816486239433,
            -0.27154287695884705,
            0.023178402334451675
        ],
        [
            -0.023158859461545944,
            -0.21788005530834198,
            -0.024579621851444244
        ],
        [
            -0.02773832529783249,
            -0.28777626156806946,
            -0.0028560159262269735
        ],
        [
            -0.005956775974482298,
            -0.33101561665534973,
            -0.0281117781996727
        ],
        [
            0.03903169184923172,
            -0.32116955518722534,
            -0.02120814099907875
        ],
        [
            -0.015130911953747272,
            -0.28426480293273926,
            -0.03145736828446388
        ],
        [
            0.02361551858484745,
            -0.14305514097213745,
            -0.011171704158186913
        ],
        [
            -0.022943764925003052,
            -0.23376816511154175,
            0.004003315698355436
        ],
        [
            -0.012916146777570248,
            -0.24295049905776978,
            -0.021439818665385246
        ],
        [
            -0.007708746008574963,
            -0.1389906257390976,
            -0.018647994846105576
        ],
        [
            -0.02071657031774521,
            -0.2516474425792694,
            -0.018706368282437325
        ],
        [
            0.033661503344774246,
            -0.3175988793373108,
            -0.056184690445661545
        ],
        [
            -0.0006400584825314581,
            -0.17368154227733612,
            0.0002701991470530629
        ],
        [
            0.006351558491587639,
            -0.141349658370018,
            0.017076881602406502
        ],
        [
            -0.035395096987485886,
            -0.2160681188106537,
            0.007088860496878624
        ],
        [
            -0.01856956258416176,
            -0.24349617958068848,
            0.023016376420855522
        ]
    ],
    "radii": [
        0.035837430506944656,
        0.04417261481285095,
        0.056766100227832794,
        0.040947698056697845,
        0.04012707620859146,
        0.04478498920798302,
        0.03746344521641731,
        0.028757531195878983,
        0.0348796583712101,
        0.030103912577033043,
        0.029187923297286034,
        0.052365031093358994,
        0.03815522789955139,
        0.033946674317121506,
        0.04469451308250427,
        0.0333421565592289,
        0.04261147975921631,
        0.034497931599617004,
        0.04092458263039589,
        0.042279090732336044
    ],
    "masses": [
        0.1927965134382248,
        0.3610338568687439,
        0.7662240266799927,
        0.28759217262268066,
        0.27064570784568787,
        0.3762582540512085,
        0.22024787962436676,
        0.09961927682161331,
        0.17774821817874908,
        0.11427662521600723,
        0.10415933281183243,
        0.6014682650566101,
        0.23267555236816406,
        0.16386276483535767,
        0.3739824593067169,
        0.15526360273361206,
        0.3240920901298523,
        0.1719759851694107,
        0.28710541129112244,
        0.3165668845176697
    ],
    "mesh_path": "/Users/nn/devenv/MorphIt-1/web/examples/valkyrie/model/meshes/arms/aj3_right.dae",
    "num_spheres": 20,
    "per_sphere_mass": false,
    "config": {
        "model": {
            "num_spheres": 20,
            "mesh_path": "/Users/nn/devenv/MorphIt-1/web/examples/valkyrie/model/meshes/arms/aj3_right.dae",
            "device": "cpu",
            "initial_radius_variation": 0.1,
            "num_inside_samples": 5000,
            "num_surface_samples": 5000,
            "max_spheres": 25,
            "density": 1000.0,
            "per_sphere_mass": false
        },
        "training": {
            "iterations": 200,
            "verbose_frequency": 50,
            "logging_enabled": false,
            "center_lr": 0.002,
            "radius_lr": 0.005,
            "mass_lr": 0.01,
            "grad_clip_norm": 1.0,
            "coverage_weight": 1500.0,
            "overlap_weight": 0.3,
            "boundary_weight": 1.0,
            "surface_weight": 50.0,
            "containment_weight": 10.0,
            "sqem_weight": 3000.0,
            "mass_weight": 0.0,
            "com_weight": 0.0,
            "inertia_weight": 0.0,
            "flatness_weight": 0.0,
            "hausdorff_weight": 0.0,
            "mesh_containment_weight": 10.0,
            "early_stopping": false,
            "convergence_patience": 50,
            "convergence_threshold": 0.001,
            "density_control_enabled": true,
            "density_control_min_interval": 160,
            "density_control_patience": 1,
            "density_control_grad_threshold": 0.0001,
            "density_control_warmup_steps": 10,
            "density_control_cooling_factor": 0.85,
            "density_control_min_radius_fraction": 0.001
        },
        "visualization": {
            "enabled": false,
            "off_screen": true,
            "save_video": false,
            "video_filename": "sphere_filling.mp4",
            "render_interval": 5,
            "sphere_color": "blue",
            "sphere_opacity": 0.3,
            "mesh_color": "white",
            "mesh_line_width": 1.5,
            "mesh_opacity": 0.8,
            "show_sample_points": true,
            "show_surface_points": true,
            "sample_points_subsample": 100000,
            "surface_points_subsample": 100000,
            "sample_point_color": "red",
            "surface_point_color": "green",
            "point_size": 5,
            "camera_position": [
                1.0,
                1.0,
                1.0
            ],
            "camera_focal_point": [
                0.0,
                0.0,
                0.0
            ],
            "camera_view_up": [
                0.0,
                0.0,
                1.0
            ],
            "camera_azimuth": 80,
            "camera_elevation": 120,
            "camera_roll": 120,
            "camera_zoom": 1.5
        },
        "results_dir": "/Users/nn/devenv/MorphIt-1/web/examples/valkyrie.spheres/spheres",
        "output_filename": "rightShoulderYawLink_0.json",
        "random_seed": 0
    }
}